[
    {
      "title": "Responsive Web Design",
      "days": 10,
      "status": "Pending"
    },
    {
      "title": "JavaScript Algorithms and Data Structures",
      "days": 15,
      "status": "Pending"
    },
    {
      "title": "Front End Development Libraries",
      "days": 10,
      "status": "Pending"
    },
    {
        "title": "Back-End + APIs",
        "days": 12,
        "status": "Pending"
    },
    {
        "title": "Relational DB",
        "days": 8,
        "status": "Pending"
    },
    {
        "title": "Quality Assurance",
        "days": 6,
        "status": "Pending"
    },
    {
        "title": "Python Basics",
        "days": 10,
        "status": "Pending"
    },
    {
        "title": "Python Data Analysis",
        "days": 8,
        "status": "Pending"
    },
    {
        "title": "Info Security",
        "days": 6,
        "status": "Pending"
    },
    {
        "title": "Machine Learning",
        "days": 12,
        "status": "Pending"
    }
  ]
  